smtp_server/__init__.py
smtp_server/__main__.py
smtp_server/smtp_server.py
smtp_server-0.0.2.dist-info/LICENSE
smtp_server-0.0.2.dist-info/METADATA
smtp_server-0.0.2.dist-info/WHEEL
smtp_server-0.0.2.dist-info/top_level.txt
smtp_server-0.0.2.dist-info/RECORD
