Metadata-Version: 2.1
Name: smtp-server
Version: 0.0.2
Summary: Simple SMTP Server Demo
Home-page: https://github.com/linxiaohui/smtp-server
Author: Lin Xiao Hui
Author-email: llinxiaohui@126.com
License: UNKNOWN
Platform: UNKNOWN
Classifier: Programming Language :: Python :: 3
Classifier: License :: OSI Approved :: GNU General Public License v3 (GPLv3)
Classifier: Operating System :: OS Independent
Requires-Python: >=3.6
Requires-Dist: dnspython
